inv_agent/__init__.py
inv_agent/agent.py
inv_agent/annual_po.json
inv_agent/expiry_monitor.py
inv_agent/inventory_tools.py
inv_agent/logger.py
inv_agent/main.py
inv_agent/send_email_utils.py
inv_agent-0.1.2.dist-info/METADATA
inv_agent-0.1.2.dist-info/WHEEL
inv_agent-0.1.2.dist-info/RECORD
