Metadata-Version: 2.3
Name: inv-agent
Version: 0.1.2
Summary: Clinic inventory assistant powered by LLM and inventory management tools.
License: MIT
Keywords: inventory,clinic,llm,assistant
Author: pavans
Author-email: pavansakireddy@gmail.com
Requires-Python: >=3.9,<4.0
Classifier: License :: OSI Approved :: MIT License
Classifier: Programming Language :: Python :: 3
Classifier: Programming Language :: Python :: 3.9
Classifier: Programming Language :: Python :: 3.10
Classifier: Programming Language :: Python :: 3.11
Classifier: Programming Language :: Python :: 3.12
Classifier: Programming Language :: Python :: 3.13
Requires-Dist: fpdf (==1.7.2)
Requires-Dist: langchain-core (==0.3.68)
Requires-Dist: langchain-ollama (==0.3.4)
Requires-Dist: langgraph (==0.5.2)
Requires-Dist: ollama (==0.5.1)
Requires-Dist: python-dotenv (==1.1.1)
